ChangeLog.md
LICENSE
MANIFEST.in
Makefile
README.md
setup.cfg
setup.py
versioneer.py
bp/__init__.py
bp/_ba.c
bp/_ba.pxd
bp/_ba.pyx
bp/_binary_tree.c
bp/_binary_tree.pxd
bp/_binary_tree.pyx
bp/_bp.c
bp/_bp.pxd
bp/_bp.pyx
bp/_cli.py
bp/_conv.c
bp/_conv.pyx
bp/_insert.c
bp/_insert.pyx
bp/_io.c
bp/_io.pyx
bp/_version.py
bp/BitArray/.gitignore
bp/BitArray/.travis.yml
bp/BitArray/AUTHORS
bp/BitArray/LICENSE
bp/BitArray/Makefile
bp/BitArray/README.md
bp/BitArray/bar.h
bp/BitArray/bit_array.c
bp/BitArray/bit_array.h
bp/BitArray/bit_macros.h
bp/BitArray/dev/Makefile
bp/BitArray/dev/bit_array_generate.c
bp/BitArray/dev/bit_array_test.c
bp/BitArray/dev/bitlock_test.c
bp/BitArray/dev/bitlock_try_test.c
bp/BitArray/examples/Makefile
bp/BitArray/examples/example.c
bp/BitArray/examples/example.cpp
bp/tests/__init__.py
bp/tests/test_bp.py
bp/tests/test_bp_cy.c
bp/tests/test_bp_cy.pyx
bp/tests/test_conv.py
bp/tests/test_insert.py
bp/tests/test_io.py
bp/tests/data/200/placement.jplace
bp/tests/data/200/placement.newick
bp/tests/data/300/placement.full_resolve.newick
bp/tests/data/300/placement_mul.jplace
bp/tests/data/300/placement_mul.newick
iow.egg-info/PKG-INFO
iow.egg-info/SOURCES.txt
iow.egg-info/dependency_links.txt
iow.egg-info/entry_points.txt
iow.egg-info/requires.txt
iow.egg-info/top_level.txt