Metadata-Version: 2.1
Name: iow
Version: 1.0.8
Summary: Balanced parentheses
Home-page: https://github.com/biocore/improved-octo-waddle
Author: Daniel McDonald
Author-email: damcdonald@ucsd.edu
Maintainer: Daniel McDonald
Maintainer-email: damcdonald@ucsd.edu
License-File: LICENSE
